socialregexes/__init__.py
socialregexes/socialregexes.py
socialregexes-0.1.dist-info/DESCRIPTION.rst
socialregexes-0.1.dist-info/METADATA
socialregexes-0.1.dist-info/RECORD
socialregexes-0.1.dist-info/WHEEL
socialregexes-0.1.dist-info/entry_points.txt
socialregexes-0.1.dist-info/metadata.json
socialregexes-0.1.dist-info/top_level.txt
